{
    "itemsFetched": 12,
    "itemsReturned": null,
    "skuDetail": [
      {
        "skuProduct": {
          "sku": "354872",
          "skuStyleGroup": "K2NN5743",
          "skuPlu": "27414",
          "skuDate": null,
          "barcodePrimary": "0091205953000",
          "barcodeSupplier": "0091205953000",
          "sectionDetail": {
            "sectionId": "F",
            "name": "FOOTWEAR",
            "description": "FOOTWEAR (F)"
          },
          "genderDetail": {
            "genderId": "K",
            "name": "Mens Footwear",
            "description": "Mens Footwear (K)",
            "standardGenderCode": "K"
          },
          "categoryDetail": {
            "categoryId": "K2",
            "name": "RETRO RUNNING MENS",
            "description": "RETRO RUNNING MENS (K2)"
          },
          "departmentDetail": {
            "departmentId": "K2NN",
            "name": "RETRO RUNNING MENS NIKE",
            "description": "RETRO RUNNING MENS NIKE (K2NN)"
          },
          "groupDetail": {
            "groupId": "5743",
            "name": "ROSHE TWO BLK/BLK",
            "description": "ROSHE TWO BLK/BLK (5743)"
          },
          "deptGrp": "K2NN5743",
          "description": "ROSHE TWO BLK/BLK",
          "skuSize": "6 MENS",
          "colour": "Black",
          "skuVatCode": "1",
          "manufacturer": "NIKE",
          "supplierId": "15",
          "company": null,
          "styleCode": "844656001",
          "ageRestrictedInd": false,
          "exclusiveInd": "N",
          "perennialInd": "N",
          "labelType": "S",
          "brandDetail": {
            "brandId": "15",
            "name": "NIKE",
            "description": "NIKE"
          },
          "colourDetail": {
            "colourId": "090",
            "colourName": "Black",
            "colourDescription": "Black (090)",
            "colourDescription1": null,
            "colourDescription2": null,
            "colourDescription3": null
          },
          "subCategoryId": "C8",
          "productInfoId": "27414",
          "productGroupingId": "255021",
          "defaultImage": null,
          "productInfoDetail": {
            "productInfoId": "27414",
            "title": "Roshe 2",
            "suppName": "Nike",
            "description": null,
            "mainColour": "Black",
            "secondaryColour": null,
            "fabric": "Textile & Synthetic Upper/Synthetic Sole",
            "lining": null,
            "care": null,
            "createdDate": "2016-02-05T00:00:00.000Z",
            "lastUpdatedDate": "2021-11-28T17:50:40.000Z",
            "dataSource": null
          },
          "productFaciaInfoDetail": {
            "productInfoId": "27414",
            "faciaId": "JD",
            "description": "A fresh take on a footwear classic, these men's Roshe 2 Trainers from Nike redefine simplicity. Paying a nod of respect to the original Roshe One Trainer, the black colourway will get heads turning your way for all the right reasons. Builtwith a stretch foam upper that conforms to your foot for maximum comfort when you're on the move, while the updated sole features three different foam densities for lightweight support and supreme durability. Complete with the iconic Swoosh branding to the sides for one final stamp of quality approval.",
            "createdDate": "2016-02-05T00:00:00.000Z",
            "lastUpdatedDate": "2021-11-28T17:50:40.000Z",
            "dataSource": null
          },
          "promotionDetailList": {
            "promotionDetail": [
              
            ]
          },
          "dateRestrictedDetail": null,
          "sizeDetail": {
            "mapSize": "6",
            "euSize": "40",
            "usSize": "7",
            "mappedSkuSize": "6",
            "rangeMin": "6",
            "rangeMax": "13"
          }
        },
        "skuPrice": {
          "rrpPrice": {
            "currencyCode": "GBP",
            "amount": 80.00
          },
          "currentPrice": {
            "currencyCode": "GBP",
            "amount": 3.00
          },
          "currentPriceFromDate": "2019-08-14T23:00:00.000Z",
          "originalPrice": {
            "currencyCode": "GBP",
            "amount": 80.00
          },
          "wasPrice": {
            "currencyCode": "GBP",
            "amount": 80.00
          },
          "previousPrice": {
            "currencyCode": "GBP",
            "amount": 5.00
          },
          "previousPriceFromDate": "2018-06-19T23:00:00.000Z",
          "pendingPrice": null,
          "pendingPriceFromDate": null,
          "noTicket": "N"
        },
        "skuStock": {
          "stockLevelQuantity": 0,
          "idealQuantity": 0,
          "scheduledQuantity": 0,
          "allocatedQuantity": 0,
          "transitInQuantity": 0,
          "transitOutQuantity": 0,
          "lastSoldDate": null,
          "locationQuantity": 0,
          "dueStockQuantity": 0,
          "shelfNo": null,
          "stockStatus": null,
          "stockCode": null
        },
        "skuDivision": {
          "buyerId": "3",
          "continuityInd": false
        },
        "skuVatRate": {
          "vatDesc": "STAND",
          "vatRate": 20
        }
      },
      {
        "skuProduct": {
          "sku": "354873",
          "skuStyleGroup": "K2NN5743",
          "skuPlu": "27414",
          "skuDate": null,
          "barcodePrimary": "0091205953253",
          "barcodeSupplier": "0091205953253",
          "sectionDetail": {
            "sectionId": "F",
            "name": "FOOTWEAR",
            "description": "FOOTWEAR (F)"
          },
          "genderDetail": {
            "genderId": "K",
            "name": "Mens Footwear",
            "description": "Mens Footwear (K)",
            "standardGenderCode": "K"
          },
          "categoryDetail": {
            "categoryId": "K2",
            "name": "RETRO RUNNING MENS",
            "description": "RETRO RUNNING MENS (K2)"
          },
          "departmentDetail": {
            "departmentId": "K2NN",
            "name": "RETRO RUNNING MENS NIKE",
            "description": "RETRO RUNNING MENS NIKE (K2NN)"
          },
          "groupDetail": {
            "groupId": "5743",
            "name": "ROSHE TWO BLK/BLK",
            "description": "ROSHE TWO BLK/BLK (5743)"
          },
          "deptGrp": "K2NN5743",
          "description": "ROSHE TWO BLK/BLK",
          "skuSize": "7 MENS",
          "colour": "Black",
          "skuVatCode": "1",
          "manufacturer": "NIKE",
          "supplierId": "15",
          "company": null,
          "styleCode": "844656001",
          "ageRestrictedInd": false,
          "exclusiveInd": "N",
          "perennialInd": "N",
          "labelType": "S",
          "brandDetail": {
            "brandId": "15",
            "name": "NIKE",
            "description": "NIKE"
          },
          "colourDetail": {
            "colourId": "090",
            "colourName": "Black",
            "colourDescription": "Black (090)",
            "colourDescription1": null,
            "colourDescription2": null,
            "colourDescription3": null
          },
          "subCategoryId": "C8",
          "productInfoId": "27414",
          "productGroupingId": "255021",
          "defaultImage": null,
          "productInfoDetail": {
            "productInfoId": "27414",
            "title": "Roshe 2",
            "suppName": "Nike",
            "description": null,
            "mainColour": "Black",
            "secondaryColour": null,
            "fabric": "Textile & Synthetic Upper/Synthetic Sole",
            "lining": null,
            "care": null,
            "createdDate": "2016-02-05T00:00:00.000Z",
            "lastUpdatedDate": "2021-11-28T17:50:40.000Z",
            "dataSource": null
          },
          "productFaciaInfoDetail": {
            "productInfoId": "27414",
            "faciaId": "JD",
            "description": "A fresh take on a footwear classic, these men's Roshe 2 Trainers from Nike redefine simplicity. Paying a nod of respect to the original Roshe One Trainer, the black colourway will get heads turning your way for all the right reasons. Builtwith a stretch foam upper that conforms to your foot for maximum comfort when you're on the move, while the updated sole features three different foam densities for lightweight support and supreme durability. Complete with the iconic Swoosh branding to the sides for one final stamp of quality approval.",
            "createdDate": "2016-02-05T00:00:00.000Z",
            "lastUpdatedDate": "2021-11-28T17:50:40.000Z",
            "dataSource": null
          },
          "promotionDetailList": {
            "promotionDetail": [
              
            ]
          },
          "dateRestrictedDetail": null,
          "sizeDetail": {
            "mapSize": "7",
            "euSize": "41",
            "usSize": "8",
            "mappedSkuSize": "7",
            "rangeMin": "6",
            "rangeMax": "13"
          }
        },
        "skuPrice": {
          "rrpPrice": {
            "currencyCode": "GBP",
            "amount": 80.00
          },
          "currentPrice": {
            "currencyCode": "GBP",
            "amount": 3.00
          },
          "currentPriceFromDate": "2019-08-14T23:00:00.000Z",
          "originalPrice": {
            "currencyCode": "GBP",
            "amount": 80.00
          },
          "wasPrice": {
            "currencyCode": "GBP",
            "amount": 80.00
          },
          "previousPrice": {
            "currencyCode": "GBP",
            "amount": 5.00
          },
          "previousPriceFromDate": "2018-06-19T23:00:00.000Z",
          "pendingPrice": null,
          "pendingPriceFromDate": null,
          "noTicket": "N"
        },
        "skuStock": {
          "stockLevelQuantity": 0,
          "idealQuantity": 0,
          "scheduledQuantity": 0,
          "allocatedQuantity": 0,
          "transitInQuantity": 0,
          "transitOutQuantity": 0,
          "lastSoldDate": null,
          "locationQuantity": 0,
          "dueStockQuantity": 0,
          "shelfNo": null,
          "stockStatus": null,
          "stockCode": null
        },
        "skuDivision": {
          "buyerId": "3",
          "continuityInd": false
        },
        "skuVatRate": {
          "vatDesc": "STAND",
          "vatRate": 20
        }
      },
      {
        "skuProduct": {
          "sku": "354874",
          "skuStyleGroup": "K2NN5743",
          "skuPlu": "27414",
          "skuDate": null,
          "barcodePrimary": "0091205953260",
          "barcodeSupplier": "0091205953260",
          "sectionDetail": {
            "sectionId": "F",
            "name": "FOOTWEAR",
            "description": "FOOTWEAR (F)"
          },
          "genderDetail": {
            "genderId": "K",
            "name": "Mens Footwear",
            "description": "Mens Footwear (K)",
            "standardGenderCode": "K"
          },
          "categoryDetail": {
            "categoryId": "K2",
            "name": "RETRO RUNNING MENS",
            "description": "RETRO RUNNING MENS (K2)"
          },
          "departmentDetail": {
            "departmentId": "K2NN",
            "name": "RETRO RUNNING MENS NIKE",
            "description": "RETRO RUNNING MENS NIKE (K2NN)"
          },
          "groupDetail": {
            "groupId": "5743",
            "name": "ROSHE TWO BLK/BLK",
            "description": "ROSHE TWO BLK/BLK (5743)"
          },
          "deptGrp": "K2NN5743",
          "description": "ROSHE TWO BLK/BLK",
          "skuSize": "7*MENS",
          "colour": "Black",
          "skuVatCode": "1",
          "manufacturer": "NIKE",
          "supplierId": "15",
          "company": null,
          "styleCode": "844656001",
          "ageRestrictedInd": false,
          "exclusiveInd": "N",
          "perennialInd": "N",
          "labelType": "S",
          "brandDetail": {
            "brandId": "15",
            "name": "NIKE",
            "description": "NIKE"
          },
          "colourDetail": {
            "colourId": "090",
            "colourName": "Black",
            "colourDescription": "Black (090)",
            "colourDescription1": null,
            "colourDescription2": null,
            "colourDescription3": null
          },
          "subCategoryId": "C8",
          "productInfoId": "27414",
          "productGroupingId": "255021",
          "defaultImage": null,
          "productInfoDetail": {
            "productInfoId": "27414",
            "title": "Roshe 2",
            "suppName": "Nike",
            "description": null,
            "mainColour": "Black",
            "secondaryColour": null,
            "fabric": "Textile & Synthetic Upper/Synthetic Sole",
            "lining": null,
            "care": null,
            "createdDate": "2016-02-05T00:00:00.000Z",
            "lastUpdatedDate": "2021-11-28T17:50:40.000Z",
            "dataSource": null
          },
          "productFaciaInfoDetail": {
            "productInfoId": "27414",
            "faciaId": "JD",
            "description": "A fresh take on a footwear classic, these men's Roshe 2 Trainers from Nike redefine simplicity. Paying a nod of respect to the original Roshe One Trainer, the black colourway will get heads turning your way for all the right reasons. Builtwith a stretch foam upper that conforms to your foot for maximum comfort when you're on the move, while the updated sole features three different foam densities for lightweight support and supreme durability. Complete with the iconic Swoosh branding to the sides for one final stamp of quality approval.",
            "createdDate": "2016-02-05T00:00:00.000Z",
            "lastUpdatedDate": "2021-11-28T17:50:40.000Z",
            "dataSource": null
          },
          "promotionDetailList": {
            "promotionDetail": [
              
            ]
          },
          "dateRestrictedDetail": null,
          "sizeDetail": {
            "mapSize": "7.5",
            "euSize": "42",
            "usSize": "8.5",
            "mappedSkuSize": "7.5",
            "rangeMin": "6",
            "rangeMax": "13"
          }
        },
        "skuPrice": {
          "rrpPrice": {
            "currencyCode": "GBP",
            "amount": 80.00
          },
          "currentPrice": {
            "currencyCode": "GBP",
            "amount": 3.00
          },
          "currentPriceFromDate": "2019-08-14T23:00:00.000Z",
          "originalPrice": {
            "currencyCode": "GBP",
            "amount": 80.00
          },
          "wasPrice": {
            "currencyCode": "GBP",
            "amount": 80.00
          },
          "previousPrice": {
            "currencyCode": "GBP",
            "amount": 5.00
          },
          "previousPriceFromDate": "2018-06-19T23:00:00.000Z",
          "pendingPrice": null,
          "pendingPriceFromDate": null,
          "noTicket": "N"
        },
        "skuStock": {
          "stockLevelQuantity": 0,
          "idealQuantity": 0,
          "scheduledQuantity": 0,
          "allocatedQuantity": 0,
          "transitInQuantity": 0,
          "transitOutQuantity": 0,
          "lastSoldDate": null,
          "locationQuantity": 0,
          "dueStockQuantity": 0,
          "shelfNo": null,
          "stockStatus": null,
          "stockCode": null
        },
        "skuDivision": {
          "buyerId": "3",
          "continuityInd": false
        },
        "skuVatRate": {
          "vatDesc": "STAND",
          "vatRate": 20
        }
      },
      {
        "skuProduct": {
          "sku": "354889",
          "skuStyleGroup": "K2NN5743",
          "skuPlu": "27414",
          "skuDate": null,
          "barcodePrimary": "0091205953277",
          "barcodeSupplier": "0091205953277",
          "sectionDetail": {
            "sectionId": "F",
            "name": "FOOTWEAR",
            "description": "FOOTWEAR (F)"
          },
          "genderDetail": {
            "genderId": "K",
            "name": "Mens Footwear",
            "description": "Mens Footwear (K)",
            "standardGenderCode": "K"
          },
          "categoryDetail": {
            "categoryId": "K2",
            "name": "RETRO RUNNING MENS",
            "description": "RETRO RUNNING MENS (K2)"
          },
          "departmentDetail": {
            "departmentId": "K2NN",
            "name": "RETRO RUNNING MENS NIKE",
            "description": "RETRO RUNNING MENS NIKE (K2NN)"
          },
          "groupDetail": {
            "groupId": "5743",
            "name": "ROSHE TWO BLK/BLK",
            "description": "ROSHE TWO BLK/BLK (5743)"
          },
          "deptGrp": "K2NN5743",
          "description": "ROSHE TWO BLK/BLK",
          "skuSize": "8 MENS",
          "colour": "Black",
          "skuVatCode": "1",
          "manufacturer": "NIKE",
          "supplierId": "15",
          "company": null,
          "styleCode": "844656001",
          "ageRestrictedInd": false,
          "exclusiveInd": "N",
          "perennialInd": "N",
          "labelType": "S",
          "brandDetail": {
            "brandId": "15",
            "name": "NIKE",
            "description": "NIKE"
          },
          "colourDetail": {
            "colourId": "090",
            "colourName": "Black",
            "colourDescription": "Black (090)",
            "colourDescription1": null,
            "colourDescription2": null,
            "colourDescription3": null
          },
          "subCategoryId": "C8",
          "productInfoId": "27414",
          "productGroupingId": "255021",
          "defaultImage": null,
          "productInfoDetail": {
            "productInfoId": "27414",
            "title": "Roshe 2",
            "suppName": "Nike",
            "description": null,
            "mainColour": "Black",
            "secondaryColour": null,
            "fabric": "Textile & Synthetic Upper/Synthetic Sole",
            "lining": null,
            "care": null,
            "createdDate": "2016-02-05T00:00:00.000Z",
            "lastUpdatedDate": "2021-11-28T17:50:40.000Z",
            "dataSource": null
          },
          "productFaciaInfoDetail": {
            "productInfoId": "27414",
            "faciaId": "JD",
            "description": "A fresh take on a footwear classic, these men's Roshe 2 Trainers from Nike redefine simplicity. Paying a nod of respect to the original Roshe One Trainer, the black colourway will get heads turning your way for all the right reasons. Builtwith a stretch foam upper that conforms to your foot for maximum comfort when you're on the move, while the updated sole features three different foam densities for lightweight support and supreme durability. Complete with the iconic Swoosh branding to the sides for one final stamp of quality approval.",
            "createdDate": "2016-02-05T00:00:00.000Z",
            "lastUpdatedDate": "2021-11-28T17:50:40.000Z",
            "dataSource": null
          },
          "promotionDetailList": {
            "promotionDetail": [
              
            ]
          },
          "dateRestrictedDetail": null,
          "sizeDetail": {
            "mapSize": "8",
            "euSize": "42.5",
            "usSize": "9",
            "mappedSkuSize": "8",
            "rangeMin": "6",
            "rangeMax": "13"
          }
        },
        "skuPrice": {
          "rrpPrice": {
            "currencyCode": "GBP",
            "amount": 80.00
          },
          "currentPrice": {
            "currencyCode": "GBP",
            "amount": 3.00
          },
          "currentPriceFromDate": "2019-08-14T23:00:00.000Z",
          "originalPrice": {
            "currencyCode": "GBP",
            "amount": 80.00
          },
          "wasPrice": {
            "currencyCode": "GBP",
            "amount": 80.00
          },
          "previousPrice": {
            "currencyCode": "GBP",
            "amount": 5.00
          },
          "previousPriceFromDate": "2018-06-19T23:00:00.000Z",
          "pendingPrice": null,
          "pendingPriceFromDate": null,
          "noTicket": "N"
        },
        "skuStock": {
          "stockLevelQuantity": 0,
          "idealQuantity": 0,
          "scheduledQuantity": 0,
          "allocatedQuantity": 0,
          "transitInQuantity": 0,
          "transitOutQuantity": 0,
          "lastSoldDate": null,
          "locationQuantity": 0,
          "dueStockQuantity": 0,
          "shelfNo": null,
          "stockStatus": null,
          "stockCode": null
        },
        "skuDivision": {
          "buyerId": "3",
          "continuityInd": false
        },
        "skuVatRate": {
          "vatDesc": "STAND",
          "vatRate": 20
        }
      },
      {
        "skuProduct": {
          "sku": "354909",
          "skuStyleGroup": "K2NN5743",
          "skuPlu": "27414",
          "skuDate": null,
          "barcodePrimary": "0091205953284",
          "barcodeSupplier": "0091205953284",
          "sectionDetail": {
            "sectionId": "F",
            "name": "FOOTWEAR",
            "description": "FOOTWEAR (F)"
          },
          "genderDetail": {
            "genderId": "K",
            "name": "Mens Footwear",
            "description": "Mens Footwear (K)",
            "standardGenderCode": "K"
          },
          "categoryDetail": {
            "categoryId": "K2",
            "name": "RETRO RUNNING MENS",
            "description": "RETRO RUNNING MENS (K2)"
          },
          "departmentDetail": {
            "departmentId": "K2NN",
            "name": "RETRO RUNNING MENS NIKE",
            "description": "RETRO RUNNING MENS NIKE (K2NN)"
          },
          "groupDetail": {
            "groupId": "5743",
            "name": "ROSHE TWO BLK/BLK",
            "description": "ROSHE TWO BLK/BLK (5743)"
          },
          "deptGrp": "K2NN5743",
          "description": "ROSHE TWO BLK/BLK",
          "skuSize": "8*MENS",
          "colour": "Black",
          "skuVatCode": "1",
          "manufacturer": "NIKE",
          "supplierId": "15",
          "company": null,
          "styleCode": "844656001",
          "ageRestrictedInd": false,
          "exclusiveInd": "N",
          "perennialInd": "N",
          "labelType": "S",
          "brandDetail": {
            "brandId": "15",
            "name": "NIKE",
            "description": "NIKE"
          },
          "colourDetail": {
            "colourId": "090",
            "colourName": "Black",
            "colourDescription": "Black (090)",
            "colourDescription1": null,
            "colourDescription2": null,
            "colourDescription3": null
          },
          "subCategoryId": "C8",
          "productInfoId": "27414",
          "productGroupingId": "255021",
          "defaultImage": null,
          "productInfoDetail": {
            "productInfoId": "27414",
            "title": "Roshe 2",
            "suppName": "Nike",
            "description": null,
            "mainColour": "Black",
            "secondaryColour": null,
            "fabric": "Textile & Synthetic Upper/Synthetic Sole",
            "lining": null,
            "care": null,
            "createdDate": "2016-02-05T00:00:00.000Z",
            "lastUpdatedDate": "2021-11-28T17:50:40.000Z",
            "dataSource": null
          },
          "productFaciaInfoDetail": {
            "productInfoId": "27414",
            "faciaId": "JD",
            "description": "A fresh take on a footwear classic, these men's Roshe 2 Trainers from Nike redefine simplicity. Paying a nod of respect to the original Roshe One Trainer, the black colourway will get heads turning your way for all the right reasons. Builtwith a stretch foam upper that conforms to your foot for maximum comfort when you're on the move, while the updated sole features three different foam densities for lightweight support and supreme durability. Complete with the iconic Swoosh branding to the sides for one final stamp of quality approval.",
            "createdDate": "2016-02-05T00:00:00.000Z",
            "lastUpdatedDate": "2021-11-28T17:50:40.000Z",
            "dataSource": null
          },
          "promotionDetailList": {
            "promotionDetail": [
              
            ]
          },
          "dateRestrictedDetail": null,
          "sizeDetail": {
            "mapSize": "8.5",
            "euSize": "43",
            "usSize": "9.5",
            "mappedSkuSize": "8.5",
            "rangeMin": "6",
            "rangeMax": "13"
          }
        },
        "skuPrice": {
          "rrpPrice": {
            "currencyCode": "GBP",
            "amount": 80.00
          },
          "currentPrice": {
            "currencyCode": "GBP",
            "amount": 3.00
          },
          "currentPriceFromDate": "2019-08-14T23:00:00.000Z",
          "originalPrice": {
            "currencyCode": "GBP",
            "amount": 80.00
          },
          "wasPrice": {
            "currencyCode": "GBP",
            "amount": 80.00
          },
          "previousPrice": {
            "currencyCode": "GBP",
            "amount": 5.00
          },
          "previousPriceFromDate": "2018-06-19T23:00:00.000Z",
          "pendingPrice": null,
          "pendingPriceFromDate": null,
          "noTicket": "N"
        },
        "skuStock": {
          "stockLevelQuantity": 0,
          "idealQuantity": 0,
          "scheduledQuantity": 0,
          "allocatedQuantity": 0,
          "transitInQuantity": 0,
          "transitOutQuantity": 0,
          "lastSoldDate": null,
          "locationQuantity": 0,
          "dueStockQuantity": 0,
          "shelfNo": null,
          "stockStatus": null,
          "stockCode": null
        },
        "skuDivision": {
          "buyerId": "3",
          "continuityInd": false
        },
        "skuVatRate": {
          "vatDesc": "STAND",
          "vatRate": 20
        }
      },
      {
        "skuProduct": {
          "sku": "354915",
          "skuStyleGroup": "K2NN5743",
          "skuPlu": "27414",
          "skuDate": null,
          "barcodePrimary": "0091205953451",
          "barcodeSupplier": "0091205953451",
          "sectionDetail": {
            "sectionId": "F",
            "name": "FOOTWEAR",
            "description": "FOOTWEAR (F)"
          },
          "genderDetail": {
            "genderId": "K",
            "name": "Mens Footwear",
            "description": "Mens Footwear (K)",
            "standardGenderCode": "K"
          },
          "categoryDetail": {
            "categoryId": "K2",
            "name": "RETRO RUNNING MENS",
            "description": "RETRO RUNNING MENS (K2)"
          },
          "departmentDetail": {
            "departmentId": "K2NN",
            "name": "RETRO RUNNING MENS NIKE",
            "description": "RETRO RUNNING MENS NIKE (K2NN)"
          },
          "groupDetail": {
            "groupId": "5743",
            "name": "ROSHE TWO BLK/BLK",
            "description": "ROSHE TWO BLK/BLK (5743)"
          },
          "deptGrp": "K2NN5743",
          "description": "ROSHE TWO BLK/BLK",
          "skuSize": "9 MENS",
          "colour": "Black",
          "skuVatCode": "1",
          "manufacturer": "NIKE",
          "supplierId": "15",
          "company": null,
          "styleCode": "844656001",
          "ageRestrictedInd": false,
          "exclusiveInd": "N",
          "perennialInd": "N",
          "labelType": "S",
          "brandDetail": {
            "brandId": "15",
            "name": "NIKE",
            "description": "NIKE"
          },
          "colourDetail": {
            "colourId": "090",
            "colourName": "Black",
            "colourDescription": "Black (090)",
            "colourDescription1": null,
            "colourDescription2": null,
            "colourDescription3": null
          },
          "subCategoryId": "C8",
          "productInfoId": "27414",
          "productGroupingId": "255021",
          "defaultImage": null,
          "productInfoDetail": {
            "productInfoId": "27414",
            "title": "Roshe 2",
            "suppName": "Nike",
            "description": null,
            "mainColour": "Black",
            "secondaryColour": null,
            "fabric": "Textile & Synthetic Upper/Synthetic Sole",
            "lining": null,
            "care": null,
            "createdDate": "2016-02-05T00:00:00.000Z",
            "lastUpdatedDate": "2021-11-28T17:50:40.000Z",
            "dataSource": null
          },
          "productFaciaInfoDetail": {
            "productInfoId": "27414",
            "faciaId": "JD",
            "description": "A fresh take on a footwear classic, these men's Roshe 2 Trainers from Nike redefine simplicity. Paying a nod of respect to the original Roshe One Trainer, the black colourway will get heads turning your way for all the right reasons. Builtwith a stretch foam upper that conforms to your foot for maximum comfort when you're on the move, while the updated sole features three different foam densities for lightweight support and supreme durability. Complete with the iconic Swoosh branding to the sides for one final stamp of quality approval.",
            "createdDate": "2016-02-05T00:00:00.000Z",
            "lastUpdatedDate": "2021-11-28T17:50:40.000Z",
            "dataSource": null
          },
          "promotionDetailList": {
            "promotionDetail": [
              
            ]
          },
          "dateRestrictedDetail": null,
          "sizeDetail": {
            "mapSize": "9",
            "euSize": "44",
            "usSize": "10",
            "mappedSkuSize": "9",
            "rangeMin": "6",
            "rangeMax": "13"
          }
        },
        "skuPrice": {
          "rrpPrice": {
            "currencyCode": "GBP",
            "amount": 80.00
          },
          "currentPrice": {
            "currencyCode": "GBP",
            "amount": 3.00
          },
          "currentPriceFromDate": "2019-08-14T23:00:00.000Z",
          "originalPrice": {
            "currencyCode": "GBP",
            "amount": 80.00
          },
          "wasPrice": {
            "currencyCode": "GBP",
            "amount": 80.00
          },
          "previousPrice": {
            "currencyCode": "GBP",
            "amount": 5.00
          },
          "previousPriceFromDate": "2018-06-19T23:00:00.000Z",
          "pendingPrice": null,
          "pendingPriceFromDate": null,
          "noTicket": "N"
        },
        "skuStock": {
          "stockLevelQuantity": 0,
          "idealQuantity": 0,
          "scheduledQuantity": 0,
          "allocatedQuantity": 0,
          "transitInQuantity": 0,
          "transitOutQuantity": 0,
          "lastSoldDate": null,
          "locationQuantity": 0,
          "dueStockQuantity": 0,
          "shelfNo": null,
          "stockStatus": null,
          "stockCode": null
        },
        "skuDivision": {
          "buyerId": "3",
          "continuityInd": false
        },
        "skuVatRate": {
          "vatDesc": "STAND",
          "vatRate": 20
        }
      },
      {
        "skuProduct": {
          "sku": "354917",
          "skuStyleGroup": "K2NN5743",
          "skuPlu": "27414",
          "skuDate": null,
          "barcodePrimary": "0091205953543",
          "barcodeSupplier": "0091205953543",
          "sectionDetail": {
            "sectionId": "F",
            "name": "FOOTWEAR",
            "description": "FOOTWEAR (F)"
          },
          "genderDetail": {
            "genderId": "K",
            "name": "Mens Footwear",
            "description": "Mens Footwear (K)",
            "standardGenderCode": "K"
          },
          "categoryDetail": {
            "categoryId": "K2",
            "name": "RETRO RUNNING MENS",
            "description": "RETRO RUNNING MENS (K2)"
          },
          "departmentDetail": {
            "departmentId": "K2NN",
            "name": "RETRO RUNNING MENS NIKE",
            "description": "RETRO RUNNING MENS NIKE (K2NN)"
          },
          "groupDetail": {
            "groupId": "5743",
            "name": "ROSHE TWO BLK/BLK",
            "description": "ROSHE TWO BLK/BLK (5743)"
          },
          "deptGrp": "K2NN5743",
          "description": "ROSHE TWO BLK/BLK",
          "skuSize": "9*MENS",
          "colour": "Black",
          "skuVatCode": "1",
          "manufacturer": "NIKE",
          "supplierId": "15",
          "company": null,
          "styleCode": "844656001",
          "ageRestrictedInd": false,
          "exclusiveInd": "N",
          "perennialInd": "N",
          "labelType": "S",
          "brandDetail": {
            "brandId": "15",
            "name": "NIKE",
            "description": "NIKE"
          },
          "colourDetail": {
            "colourId": "090",
            "colourName": "Black",
            "colourDescription": "Black (090)",
            "colourDescription1": null,
            "colourDescription2": null,
            "colourDescription3": null
          },
          "subCategoryId": "C8",
          "productInfoId": "27414",
          "productGroupingId": "255021",
          "defaultImage": null,
          "productInfoDetail": {
            "productInfoId": "27414",
            "title": "Roshe 2",
            "suppName": "Nike",
            "description": null,
            "mainColour": "Black",
            "secondaryColour": null,
            "fabric": "Textile & Synthetic Upper/Synthetic Sole",
            "lining": null,
            "care": null,
            "createdDate": "2016-02-05T00:00:00.000Z",
            "lastUpdatedDate": "2021-11-28T17:50:40.000Z",
            "dataSource": null
          },
          "productFaciaInfoDetail": {
            "productInfoId": "27414",
            "faciaId": "JD",
            "description": "A fresh take on a footwear classic, these men's Roshe 2 Trainers from Nike redefine simplicity. Paying a nod of respect to the original Roshe One Trainer, the black colourway will get heads turning your way for all the right reasons. Builtwith a stretch foam upper that conforms to your foot for maximum comfort when you're on the move, while the updated sole features three different foam densities for lightweight support and supreme durability. Complete with the iconic Swoosh branding to the sides for one final stamp of quality approval.",
            "createdDate": "2016-02-05T00:00:00.000Z",
            "lastUpdatedDate": "2021-11-28T17:50:40.000Z",
            "dataSource": null
          },
          "promotionDetailList": {
            "promotionDetail": [
              
            ]
          },
          "dateRestrictedDetail": null,
          "sizeDetail": {
            "mapSize": "9.5",
            "euSize": "44.5",
            "usSize": "10.5",
            "mappedSkuSize": "9.5",
            "rangeMin": "6",
            "rangeMax": "13"
          }
        },
        "skuPrice": {
          "rrpPrice": {
            "currencyCode": "GBP",
            "amount": 80.00
          },
          "currentPrice": {
            "currencyCode": "GBP",
            "amount": 3.00
          },
          "currentPriceFromDate": "2019-08-14T23:00:00.000Z",
          "originalPrice": {
            "currencyCode": "GBP",
            "amount": 80.00
          },
          "wasPrice": {
            "currencyCode": "GBP",
            "amount": 80.00
          },
          "previousPrice": {
            "currencyCode": "GBP",
            "amount": 5.00
          },
          "previousPriceFromDate": "2018-06-19T23:00:00.000Z",
          "pendingPrice": null,
          "pendingPriceFromDate": null,
          "noTicket": "N"
        },
        "skuStock": {
          "stockLevelQuantity": 0,
          "idealQuantity": 0,
          "scheduledQuantity": 0,
          "allocatedQuantity": 0,
          "transitInQuantity": 0,
          "transitOutQuantity": 0,
          "lastSoldDate": null,
          "locationQuantity": 0,
          "dueStockQuantity": 0,
          "shelfNo": null,
          "stockStatus": null,
          "stockCode": null
        },
        "skuDivision": {
          "buyerId": "3",
          "continuityInd": false
        },
        "skuVatRate": {
          "vatDesc": "STAND",
          "vatRate": 20
        }
      },
      {
        "skuProduct": {
          "sku": "354921",
          "skuStyleGroup": "K2NN5743",
          "skuPlu": "27414",
          "skuDate": null,
          "barcodePrimary": "0091205954786",
          "barcodeSupplier": "0091205954786",
          "sectionDetail": {
            "sectionId": "F",
            "name": "FOOTWEAR",
            "description": "FOOTWEAR (F)"
          },
          "genderDetail": {
            "genderId": "K",
            "name": "Mens Footwear",
            "description": "Mens Footwear (K)",
            "standardGenderCode": "K"
          },
          "categoryDetail": {
            "categoryId": "K2",
            "name": "RETRO RUNNING MENS",
            "description": "RETRO RUNNING MENS (K2)"
          },
          "departmentDetail": {
            "departmentId": "K2NN",
            "name": "RETRO RUNNING MENS NIKE",
            "description": "RETRO RUNNING MENS NIKE (K2NN)"
          },
          "groupDetail": {
            "groupId": "5743",
            "name": "ROSHE TWO BLK/BLK",
            "description": "ROSHE TWO BLK/BLK (5743)"
          },
          "deptGrp": "K2NN5743",
          "description": "ROSHE TWO BLK/BLK",
          "skuSize": "10 MENS",
          "colour": "Black",
          "skuVatCode": "1",
          "manufacturer": "NIKE",
          "supplierId": "15",
          "company": null,
          "styleCode": "844656001",
          "ageRestrictedInd": false,
          "exclusiveInd": "N",
          "perennialInd": "N",
          "labelType": "S",
          "brandDetail": {
            "brandId": "15",
            "name": "NIKE",
            "description": "NIKE"
          },
          "colourDetail": {
            "colourId": "090",
            "colourName": "Black",
            "colourDescription": "Black (090)",
            "colourDescription1": null,
            "colourDescription2": null,
            "colourDescription3": null
          },
          "subCategoryId": "C8",
          "productInfoId": "27414",
          "productGroupingId": "255021",
          "defaultImage": null,
          "productInfoDetail": {
            "productInfoId": "27414",
            "title": "Roshe 2",
            "suppName": "Nike",
            "description": null,
            "mainColour": "Black",
            "secondaryColour": null,
            "fabric": "Textile & Synthetic Upper/Synthetic Sole",
            "lining": null,
            "care": null,
            "createdDate": "2016-02-05T00:00:00.000Z",
            "lastUpdatedDate": "2021-11-28T17:50:40.000Z",
            "dataSource": null
          },
          "productFaciaInfoDetail": {
            "productInfoId": "27414",
            "faciaId": "JD",
            "description": "A fresh take on a footwear classic, these men's Roshe 2 Trainers from Nike redefine simplicity. Paying a nod of respect to the original Roshe One Trainer, the black colourway will get heads turning your way for all the right reasons. Builtwith a stretch foam upper that conforms to your foot for maximum comfort when you're on the move, while the updated sole features three different foam densities for lightweight support and supreme durability. Complete with the iconic Swoosh branding to the sides for one final stamp of quality approval.",
            "createdDate": "2016-02-05T00:00:00.000Z",
            "lastUpdatedDate": "2021-11-28T17:50:40.000Z",
            "dataSource": null
          },
          "promotionDetailList": {
            "promotionDetail": [
              
            ]
          },
          "dateRestrictedDetail": null,
          "sizeDetail": {
            "mapSize": "10",
            "euSize": "45",
            "usSize": "11",
            "mappedSkuSize": "10",
            "rangeMin": "6",
            "rangeMax": "13"
          }
        },
        "skuPrice": {
          "rrpPrice": {
            "currencyCode": "GBP",
            "amount": 80.00
          },
          "currentPrice": {
            "currencyCode": "GBP",
            "amount": 3.00
          },
          "currentPriceFromDate": "2019-08-14T23:00:00.000Z",
          "originalPrice": {
            "currencyCode": "GBP",
            "amount": 80.00
          },
          "wasPrice": {
            "currencyCode": "GBP",
            "amount": 80.00
          },
          "previousPrice": {
            "currencyCode": "GBP",
            "amount": 5.00
          },
          "previousPriceFromDate": "2018-06-19T23:00:00.000Z",
          "pendingPrice": null,
          "pendingPriceFromDate": null,
          "noTicket": "N"
        },
        "skuStock": {
          "stockLevelQuantity": 0,
          "idealQuantity": 0,
          "scheduledQuantity": 0,
          "allocatedQuantity": 0,
          "transitInQuantity": 0,
          "transitOutQuantity": 0,
          "lastSoldDate": null,
          "locationQuantity": 0,
          "dueStockQuantity": 0,
          "shelfNo": null,
          "stockStatus": null,
          "stockCode": null
        },
        "skuDivision": {
          "buyerId": "3",
          "continuityInd": false
        },
        "skuVatRate": {
          "vatDesc": "STAND",
          "vatRate": 20
        }
      },
      {
        "skuProduct": {
          "sku": "354929",
          "skuStyleGroup": "K2NN5743",
          "skuPlu": "27414",
          "skuDate": null,
          "barcodePrimary": "0091205954823",
          "barcodeSupplier": "0091205954823",
          "sectionDetail": {
            "sectionId": "F",
            "name": "FOOTWEAR",
            "description": "FOOTWEAR (F)"
          },
          "genderDetail": {
            "genderId": "K",
            "name": "Mens Footwear",
            "description": "Mens Footwear (K)",
            "standardGenderCode": "K"
          },
          "categoryDetail": {
            "categoryId": "K2",
            "name": "RETRO RUNNING MENS",
            "description": "RETRO RUNNING MENS (K2)"
          },
          "departmentDetail": {
            "departmentId": "K2NN",
            "name": "RETRO RUNNING MENS NIKE",
            "description": "RETRO RUNNING MENS NIKE (K2NN)"
          },
          "groupDetail": {
            "groupId": "5743",
            "name": "ROSHE TWO BLK/BLK",
            "description": "ROSHE TWO BLK/BLK (5743)"
          },
          "deptGrp": "K2NN5743",
          "description": "ROSHE TWO BLK/BLK",
          "skuSize": "10*MENS",
          "colour": "Black",
          "skuVatCode": "1",
          "manufacturer": "NIKE",
          "supplierId": "15",
          "company": null,
          "styleCode": "844656001",
          "ageRestrictedInd": false,
          "exclusiveInd": "N",
          "perennialInd": "N",
          "labelType": "S",
          "brandDetail": {
            "brandId": "15",
            "name": "NIKE",
            "description": "NIKE"
          },
          "colourDetail": {
            "colourId": "090",
            "colourName": "Black",
            "colourDescription": "Black (090)",
            "colourDescription1": null,
            "colourDescription2": null,
            "colourDescription3": null
          },
          "subCategoryId": "C8",
          "productInfoId": "27414",
          "productGroupingId": "255021",
          "defaultImage": null,
          "productInfoDetail": {
            "productInfoId": "27414",
            "title": "Roshe 2",
            "suppName": "Nike",
            "description": null,
            "mainColour": "Black",
            "secondaryColour": null,
            "fabric": "Textile & Synthetic Upper/Synthetic Sole",
            "lining": null,
            "care": null,
            "createdDate": "2016-02-05T00:00:00.000Z",
            "lastUpdatedDate": "2021-11-28T17:50:40.000Z",
            "dataSource": null
          },
          "productFaciaInfoDetail": {
            "productInfoId": "27414",
            "faciaId": "JD",
            "description": "A fresh take on a footwear classic, these men's Roshe 2 Trainers from Nike redefine simplicity. Paying a nod of respect to the original Roshe One Trainer, the black colourway will get heads turning your way for all the right reasons. Builtwith a stretch foam upper that conforms to your foot for maximum comfort when you're on the move, while the updated sole features three different foam densities for lightweight support and supreme durability. Complete with the iconic Swoosh branding to the sides for one final stamp of quality approval.",
            "createdDate": "2016-02-05T00:00:00.000Z",
            "lastUpdatedDate": "2021-11-28T17:50:40.000Z",
            "dataSource": null
          },
          "promotionDetailList": {
            "promotionDetail": [
              
            ]
          },
          "dateRestrictedDetail": null,
          "sizeDetail": {
            "mapSize": "10.5",
            "euSize": "45.5",
            "usSize": "11.5",
            "mappedSkuSize": "10.5",
            "rangeMin": "6",
            "rangeMax": "13"
          }
        },
        "skuPrice": {
          "rrpPrice": {
            "currencyCode": "GBP",
            "amount": 80.00
          },
          "currentPrice": {
            "currencyCode": "GBP",
            "amount": 3.00
          },
          "currentPriceFromDate": "2019-08-14T23:00:00.000Z",
          "originalPrice": {
            "currencyCode": "GBP",
            "amount": 80.00
          },
          "wasPrice": {
            "currencyCode": "GBP",
            "amount": 80.00
          },
          "previousPrice": {
            "currencyCode": "GBP",
            "amount": 5.00
          },
          "previousPriceFromDate": "2018-06-19T23:00:00.000Z",
          "pendingPrice": null,
          "pendingPriceFromDate": null,
          "noTicket": "N"
        },
        "skuStock": {
          "stockLevelQuantity": 0,
          "idealQuantity": 0,
          "scheduledQuantity": 0,
          "allocatedQuantity": 0,
          "transitInQuantity": 0,
          "transitOutQuantity": 0,
          "lastSoldDate": null,
          "locationQuantity": 0,
          "dueStockQuantity": 0,
          "shelfNo": null,
          "stockStatus": null,
          "stockCode": null
        },
        "skuDivision": {
          "buyerId": "3",
          "continuityInd": false
        },
        "skuVatRate": {
          "vatDesc": "STAND",
          "vatRate": 20
        }
      },
      {
        "skuProduct": {
          "sku": "354932",
          "skuStyleGroup": "K2NN5743",
          "skuPlu": "27414",
          "skuDate": null,
          "barcodePrimary": "0091205954830",
          "barcodeSupplier": "0091205954830",
          "sectionDetail": {
            "sectionId": "F",
            "name": "FOOTWEAR",
            "description": "FOOTWEAR (F)"
          },
          "genderDetail": {
            "genderId": "K",
            "name": "Mens Footwear",
            "description": "Mens Footwear (K)",
            "standardGenderCode": "K"
          },
          "categoryDetail": {
            "categoryId": "K2",
            "name": "RETRO RUNNING MENS",
            "description": "RETRO RUNNING MENS (K2)"
          },
          "departmentDetail": {
            "departmentId": "K2NN",
            "name": "RETRO RUNNING MENS NIKE",
            "description": "RETRO RUNNING MENS NIKE (K2NN)"
          },
          "groupDetail": {
            "groupId": "5743",
            "name": "ROSHE TWO BLK/BLK",
            "description": "ROSHE TWO BLK/BLK (5743)"
          },
          "deptGrp": "K2NN5743",
          "description": "ROSHE TWO BLK/BLK",
          "skuSize": "11 MENS",
          "colour": "Black",
          "skuVatCode": "1",
          "manufacturer": "NIKE",
          "supplierId": "15",
          "company": null,
          "styleCode": "844656001",
          "ageRestrictedInd": false,
          "exclusiveInd": "N",
          "perennialInd": "N",
          "labelType": "S",
          "brandDetail": {
            "brandId": "15",
            "name": "NIKE",
            "description": "NIKE"
          },
          "colourDetail": {
            "colourId": "090",
            "colourName": "Black",
            "colourDescription": "Black (090)",
            "colourDescription1": null,
            "colourDescription2": null,
            "colourDescription3": null
          },
          "subCategoryId": "C8",
          "productInfoId": "27414",
          "productGroupingId": "255021",
          "defaultImage": null,
          "productInfoDetail": {
            "productInfoId": "27414",
            "title": "Roshe 2",
            "suppName": "Nike",
            "description": null,
            "mainColour": "Black",
            "secondaryColour": null,
            "fabric": "Textile & Synthetic Upper/Synthetic Sole",
            "lining": null,
            "care": null,
            "createdDate": "2016-02-05T00:00:00.000Z",
            "lastUpdatedDate": "2021-11-28T17:50:40.000Z",
            "dataSource": null
          },
          "productFaciaInfoDetail": {
            "productInfoId": "27414",
            "faciaId": "JD",
            "description": "A fresh take on a footwear classic, these men's Roshe 2 Trainers from Nike redefine simplicity. Paying a nod of respect to the original Roshe One Trainer, the black colourway will get heads turning your way for all the right reasons. Builtwith a stretch foam upper that conforms to your foot for maximum comfort when you're on the move, while the updated sole features three different foam densities for lightweight support and supreme durability. Complete with the iconic Swoosh branding to the sides for one final stamp of quality approval.",
            "createdDate": "2016-02-05T00:00:00.000Z",
            "lastUpdatedDate": "2021-11-28T17:50:40.000Z",
            "dataSource": null
          },
          "promotionDetailList": {
            "promotionDetail": [
              
            ]
          },
          "dateRestrictedDetail": null,
          "sizeDetail": {
            "mapSize": "11",
            "euSize": "46",
            "usSize": "12",
            "mappedSkuSize": "11",
            "rangeMin": "6",
            "rangeMax": "13"
          }
        },
        "skuPrice": {
          "rrpPrice": {
            "currencyCode": "GBP",
            "amount": 80.00
          },
          "currentPrice": {
            "currencyCode": "GBP",
            "amount": 3.00
          },
          "currentPriceFromDate": "2019-08-14T23:00:00.000Z",
          "originalPrice": {
            "currencyCode": "GBP",
            "amount": 80.00
          },
          "wasPrice": {
            "currencyCode": "GBP",
            "amount": 80.00
          },
          "previousPrice": {
            "currencyCode": "GBP",
            "amount": 5.00
          },
          "previousPriceFromDate": "2018-06-19T23:00:00.000Z",
          "pendingPrice": null,
          "pendingPriceFromDate": null,
          "noTicket": "N"
        },
        "skuStock": {
          "stockLevelQuantity": 0,
          "idealQuantity": 0,
          "scheduledQuantity": 0,
          "allocatedQuantity": 0,
          "transitInQuantity": 0,
          "transitOutQuantity": 0,
          "lastSoldDate": null,
          "locationQuantity": 0,
          "dueStockQuantity": 0,
          "shelfNo": null,
          "stockStatus": null,
          "stockCode": null
        },
        "skuDivision": {
          "buyerId": "3",
          "continuityInd": false
        },
        "skuVatRate": {
          "vatDesc": "STAND",
          "vatRate": 20
        }
      },
      {
        "skuProduct": {
          "sku": "354933",
          "skuStyleGroup": "K2NN5743",
          "skuPlu": "27414",
          "skuDate": null,
          "barcodePrimary": "0091205955141",
          "barcodeSupplier": "0091205955141",
          "sectionDetail": {
            "sectionId": "F",
            "name": "FOOTWEAR",
            "description": "FOOTWEAR (F)"
          },
          "genderDetail": {
            "genderId": "K",
            "name": "Mens Footwear",
            "description": "Mens Footwear (K)",
            "standardGenderCode": "K"
          },
          "categoryDetail": {
            "categoryId": "K2",
            "name": "RETRO RUNNING MENS",
            "description": "RETRO RUNNING MENS (K2)"
          },
          "departmentDetail": {
            "departmentId": "K2NN",
            "name": "RETRO RUNNING MENS NIKE",
            "description": "RETRO RUNNING MENS NIKE (K2NN)"
          },
          "groupDetail": {
            "groupId": "5743",
            "name": "ROSHE TWO BLK/BLK",
            "description": "ROSHE TWO BLK/BLK (5743)"
          },
          "deptGrp": "K2NN5743",
          "description": "ROSHE TWO BLK/BLK",
          "skuSize": "12 MENS",
          "colour": "Black",
          "skuVatCode": "1",
          "manufacturer": "NIKE",
          "supplierId": "15",
          "company": null,
          "styleCode": "844656001",
          "ageRestrictedInd": false,
          "exclusiveInd": "N",
          "perennialInd": "N",
          "labelType": "S",
          "brandDetail": {
            "brandId": "15",
            "name": "NIKE",
            "description": "NIKE"
          },
          "colourDetail": {
            "colourId": "090",
            "colourName": "Black",
            "colourDescription": "Black (090)",
            "colourDescription1": null,
            "colourDescription2": null,
            "colourDescription3": null
          },
          "subCategoryId": "C8",
          "productInfoId": "27414",
          "productGroupingId": "255021",
          "defaultImage": null,
          "productInfoDetail": {
            "productInfoId": "27414",
            "title": "Roshe 2",
            "suppName": "Nike",
            "description": null,
            "mainColour": "Black",
            "secondaryColour": null,
            "fabric": "Textile & Synthetic Upper/Synthetic Sole",
            "lining": null,
            "care": null,
            "createdDate": "2016-02-05T00:00:00.000Z",
            "lastUpdatedDate": "2021-11-28T17:50:40.000Z",
            "dataSource": null
          },
          "productFaciaInfoDetail": {
            "productInfoId": "27414",
            "faciaId": "JD",
            "description": "A fresh take on a footwear classic, these men's Roshe 2 Trainers from Nike redefine simplicity. Paying a nod of respect to the original Roshe One Trainer, the black colourway will get heads turning your way for all the right reasons. Builtwith a stretch foam upper that conforms to your foot for maximum comfort when you're on the move, while the updated sole features three different foam densities for lightweight support and supreme durability. Complete with the iconic Swoosh branding to the sides for one final stamp of quality approval.",
            "createdDate": "2016-02-05T00:00:00.000Z",
            "lastUpdatedDate": "2021-11-28T17:50:40.000Z",
            "dataSource": null
          },
          "promotionDetailList": {
            "promotionDetail": [
              
            ]
          },
          "dateRestrictedDetail": null,
          "sizeDetail": {
            "mapSize": "12",
            "euSize": "47.5",
            "usSize": "13",
            "mappedSkuSize": "12",
            "rangeMin": "6",
            "rangeMax": "13"
          }
        },
        "skuPrice": {
          "rrpPrice": {
            "currencyCode": "GBP",
            "amount": 80.00
          },
          "currentPrice": {
            "currencyCode": "GBP",
            "amount": 3.00
          },
          "currentPriceFromDate": "2019-08-14T23:00:00.000Z",
          "originalPrice": {
            "currencyCode": "GBP",
            "amount": 80.00
          },
          "wasPrice": {
            "currencyCode": "GBP",
            "amount": 80.00
          },
          "previousPrice": {
            "currencyCode": "GBP",
            "amount": 5.00
          },
          "previousPriceFromDate": "2018-06-19T23:00:00.000Z",
          "pendingPrice": null,
          "pendingPriceFromDate": null,
          "noTicket": "N"
        },
        "skuStock": {
          "stockLevelQuantity": 0,
          "idealQuantity": 0,
          "scheduledQuantity": 0,
          "allocatedQuantity": 0,
          "transitInQuantity": 0,
          "transitOutQuantity": 0,
          "lastSoldDate": null,
          "locationQuantity": 0,
          "dueStockQuantity": 0,
          "shelfNo": null,
          "stockStatus": null,
          "stockCode": null
        },
        "skuDivision": {
          "buyerId": "3",
          "continuityInd": false
        },
        "skuVatRate": {
          "vatDesc": "STAND",
          "vatRate": 20
        }
      },
      {
        "skuProduct": {
          "sku": "354934",
          "skuStyleGroup": "K2NN5743",
          "skuPlu": "27414",
          "skuDate": null,
          "barcodePrimary": "0091205955158",
          "barcodeSupplier": "0091205955158",
          "sectionDetail": {
            "sectionId": "F",
            "name": "FOOTWEAR",
            "description": "FOOTWEAR (F)"
          },
          "genderDetail": {
            "genderId": "K",
            "name": "Mens Footwear",
            "description": "Mens Footwear (K)",
            "standardGenderCode": "K"
          },
          "categoryDetail": {
            "categoryId": "K2",
            "name": "RETRO RUNNING MENS",
            "description": "RETRO RUNNING MENS (K2)"
          },
          "departmentDetail": {
            "departmentId": "K2NN",
            "name": "RETRO RUNNING MENS NIKE",
            "description": "RETRO RUNNING MENS NIKE (K2NN)"
          },
          "groupDetail": {
            "groupId": "5743",
            "name": "ROSHE TWO BLK/BLK",
            "description": "ROSHE TWO BLK/BLK (5743)"
          },
          "deptGrp": "K2NN5743",
          "description": "ROSHE TWO BLK/BLK",
          "skuSize": "13 MENS",
          "colour": "Black",
          "skuVatCode": "1",
          "manufacturer": "NIKE",
          "supplierId": "15",
          "company": null,
          "styleCode": "844656001",
          "ageRestrictedInd": false,
          "exclusiveInd": "N",
          "perennialInd": "N",
          "labelType": "S",
          "brandDetail": {
            "brandId": "15",
            "name": "NIKE",
            "description": "NIKE"
          },
          "colourDetail": {
            "colourId": "090",
            "colourName": "Black",
            "colourDescription": "Black (090)",
            "colourDescription1": null,
            "colourDescription2": null,
            "colourDescription3": null
          },
          "subCategoryId": "C8",
          "productInfoId": "27414",
          "productGroupingId": "255021",
          "defaultImage": null,
          "productInfoDetail": {
            "productInfoId": "27414",
            "title": "Roshe 2",
            "suppName": "Nike",
            "description": null,
            "mainColour": "Black",
            "secondaryColour": null,
            "fabric": "Textile & Synthetic Upper/Synthetic Sole",
            "lining": null,
            "care": null,
            "createdDate": "2016-02-05T00:00:00.000Z",
            "lastUpdatedDate": "2021-11-28T17:50:40.000Z",
            "dataSource": null
          },
          "productFaciaInfoDetail": {
            "productInfoId": "27414",
            "faciaId": "JD",
            "description": "A fresh take on a footwear classic, these men's Roshe 2 Trainers from Nike redefine simplicity. Paying a nod of respect to the original Roshe One Trainer, the black colourway will get heads turning your way for all the right reasons. Builtwith a stretch foam upper that conforms to your foot for maximum comfort when you're on the move, while the updated sole features three different foam densities for lightweight support and supreme durability. Complete with the iconic Swoosh branding to the sides for one final stamp of quality approval.",
            "createdDate": "2016-02-05T00:00:00.000Z",
            "lastUpdatedDate": "2021-11-28T17:50:40.000Z",
            "dataSource": null
          },
          "promotionDetailList": {
            "promotionDetail": [
              
            ]
          },
          "dateRestrictedDetail": null,
          "sizeDetail": {
            "mapSize": "13",
            "euSize": "48.5",
            "usSize": "14",
            "mappedSkuSize": "13",
            "rangeMin": "6",
            "rangeMax": "13"
          }
        },
        "skuPrice": {
          "rrpPrice": {
            "currencyCode": "GBP",
            "amount": 80.00
          },
          "currentPrice": {
            "currencyCode": "GBP",
            "amount": 3.00
          },
          "currentPriceFromDate": "2019-08-14T23:00:00.000Z",
          "originalPrice": {
            "currencyCode": "GBP",
            "amount": 80.00
          },
          "wasPrice": {
            "currencyCode": "GBP",
            "amount": 80.00
          },
          "previousPrice": {
            "currencyCode": "GBP",
            "amount": 5.00
          },
          "previousPriceFromDate": "2018-06-19T23:00:00.000Z",
          "pendingPrice": null,
          "pendingPriceFromDate": null,
          "noTicket": "N"
        },
        "skuStock": {
          "stockLevelQuantity": 0,
          "idealQuantity": 0,
          "scheduledQuantity": 0,
          "allocatedQuantity": 0,
          "transitInQuantity": 0,
          "transitOutQuantity": 0,
          "lastSoldDate": null,
          "locationQuantity": 0,
          "dueStockQuantity": 0,
          "shelfNo": null,
          "stockStatus": null,
          "stockCode": null
        },
        "skuDivision": {
          "buyerId": "3",
          "continuityInd": false
        },
        "skuVatRate": {
          "vatDesc": "STAND",
          "vatRate": 20
        }
      }
    ],
    "requestStatus": null
  }